MANIFEST.in
README.md
setup.cfg
setup.py
bin/dh_run
demonhunter/__init__.py
demonhunter/dh.py
demonhunter/info.py
demonhunter.egg-info/PKG-INFO
demonhunter.egg-info/SOURCES.txt
demonhunter.egg-info/dependency_links.txt
demonhunter.egg-info/requires.txt
demonhunter.egg-info/top_level.txt
demonhunter/core/__init__.py
demonhunter/core/config_parser.py
demonhunter/core/loggers/__init__.py
demonhunter/core/loggers/logfile.py
demonhunter/core/loggers/sqlite.py
demonhunter/nodes/__init__.py
demonhunter/nodes/honeypots/__init__.py
demonhunter/nodes/honeypots/http/__init__.py
demonhunter/nodes/honeypots/http/server.py
demonhunter/nodes/honeypots/http/apache/error.html
demonhunter/nodes/honeypots/http/apache/index.html
demonhunter/nodes/honeypots/http/nginx/error.html
demonhunter/nodes/honeypots/http/nginx/index.html
demonhunter/nodes/honeypots/telnet/__init__.py
demonhunter/nodes/honeypots/vnc/__init__.py
demonhunter/nodes/honeypots/vnc/server.py
demonhunter/nodes/master/__init__.py
demonhunter/nodes/master/ext.py
demonhunter/nodes/master/models.py
demonhunter/nodes/master/webapp.py
demonhunter/nodes/master/static/css/bootstrap.min.css
demonhunter/nodes/master/static/css/bootstrap.min.css.map
demonhunter/nodes/master/static/css/style.css
demonhunter/nodes/master/static/js/bootstrap.min.js
demonhunter/nodes/master/static/js/bootstrap.min.js.map
demonhunter/nodes/master/static/js/jquery.min.js
demonhunter/nodes/master/static/js/ws.js
demonhunter/nodes/master/templates/agents.html
demonhunter/nodes/master/templates/base.html
demonhunter/nodes/master/templates/create_agent.html
demonhunter/nodes/master/templates/create_user.html
demonhunter/nodes/master/templates/dashboard.html
demonhunter/nodes/master/templates/data.html
demonhunter/nodes/master/templates/login.html
demonhunter/nodes/master/templates/users.html