Metadata-Version: 1.1
Name: demonhunter
Version: 2.0.3
Summary: A Distributed Honeypot
Home-page: https://github.com/RevengeComing/DemonHunter
Author: Sepehr Hamzelooy
Author-email: s.hamzelooy@gmail.com
License: MIT
Keywords: honeypot honeynet agent
Platform: UNKNOWN
Classifier: Development Status :: 3 - Alpha
Classifier: Intended Audience :: Developers
Classifier: License :: OSI Approved :: MIT License
Classifier: Programming Language :: Python :: 3.5
